CHANGES.rst
CONTRIBUTORS.rst
MANIFEST.in
README.rst
bootstrap.py
buildout.cfg
setup.py
travis.cfg
collective/__init__.py
collective.recipe.logger.egg-info/PKG-INFO
collective.recipe.logger.egg-info/SOURCES.txt
collective.recipe.logger.egg-info/dependency_links.txt
collective.recipe.logger.egg-info/entry_points.txt
collective.recipe.logger.egg-info/namespace_packages.txt
collective.recipe.logger.egg-info/not-zip-safe
collective.recipe.logger.egg-info/requires.txt
collective.recipe.logger.egg-info/top_level.txt
collective/recipe/__init__.py
collective/recipe/logger/README.rst
collective/recipe/logger/__init__.py
collective/recipe/logger/config.py
collective/recipe/logger/daemon.py
collective/recipe/logger/logger.py
collective/recipe/logger/main.py
collective/recipe/logger/storage.py
collective/recipe/logger/utils.py
collective/recipe/logger/tests/__init__.py
collective/recipe/logger/tests/test_docs.py