Metadata-Version: 1.0
Name: collective.recipe.logger
Version: 0.1.0b1
Summary: This recipe logs an information into storage. It's a part of https://github.com/potar/dagger
Home-page: http://github.com/potar/collective.recipe.logger
Author: Poburynnyi Taras (potar)
Author-email: poburynnyitaras@gmail.com
License: GPL
Keywords: buildout logger
Platform: UNKNOWN
Classifier: Framework :: Buildout
Classifier: Framework :: Buildout :: Recipe
Classifier: Intended Audience :: Developers
Classifier: Topic :: Software Development :: Build Tools
Classifier: License :: OSI Approved :: GNU General Public License (GPL)
